adabmDCA/__init__.py
adabmDCA/checkpoint.py
adabmDCA/cli.py
adabmDCA/cobalt.py
adabmDCA/dataset.py
adabmDCA/dca.py
adabmDCA/fasta.py
adabmDCA/functional.py
adabmDCA/graph.py
adabmDCA/io.py
adabmDCA/parser.py
adabmDCA/plot.py
adabmDCA/resampling.py
adabmDCA/sampling.py
adabmDCA/statmech.py
adabmDCA/stats.py
adabmDCA/training.py
adabmDCA/utils.py
adabmDCA/scripts/__init__.py
adabmDCA/scripts/contacts.py
adabmDCA/scripts/convert_format_params.py
adabmDCA/scripts/dms.py
adabmDCA/scripts/energies.py
adabmDCA/scripts/profmark.py
adabmDCA/scripts/reintegrate.py
adabmDCA/scripts/sample.py
adabmDCA/scripts/td_integration.py
adabmDCA/scripts/train.py
adabmdca-0.7.dist-info/licenses/LICENSE
adabmdca-0.7.dist-info/METADATA
adabmdca-0.7.dist-info/WHEEL
adabmdca-0.7.dist-info/entry_points.txt
adabmdca-0.7.dist-info/top_level.txt
adabmdca-0.7.dist-info/RECORD
