Metadata-Version: 2.4
Name: adabmDCA
Version: 0.7
Summary: Python implementation of Direct Coupling Analysis
Home-page: https://github.com/spqb/adabmDCA
Author: Lorenzo Rosset, Roberto Netti, Anna Paola Muntoni, Francesco Zamponi, Martin Weigt
Author-email: rosset.lorenzo@gmail.com
Maintainer: Lorenzo Rosset
Classifier: Programming Language :: Python :: 3
Classifier: License :: OSI Approved :: Apache Software License
Classifier: Operating System :: OS Independent
Requires-Python: >=3.10
License-File: LICENSE
Requires-Dist: matplotlib>=3.8.0
Requires-Dist: numpy>=1.26.4
Requires-Dist: pandas>=2.2.2
Requires-Dist: torch>=2.1.0
Requires-Dist: tqdm>=4.66.6
Requires-Dist: wandb>=0.12.0
Requires-Dist: biopython>=1.85
Requires-Dist: seaborn>=0.12.2
Dynamic: author
Dynamic: author-email
Dynamic: classifier
Dynamic: description
Dynamic: description-content-type
Dynamic: home-page
Dynamic: license-file
Dynamic: maintainer
Dynamic: requires-dist
Dynamic: requires-python
Dynamic: summary
